django_blog_comments/__init__.py
django_blog_comments/admin.py
django_blog_comments/apps.py
django_blog_comments/models.py
django_blog_comments/tests.py
django_blog_comments/urls.py
django_blog_comments/views.py
django_blog_comments/migrations/0001_initial.py
django_blog_comments/migrations/__init__.py
django_blog_comments-1.0.0.dist-info/LICENSE
django_blog_comments-1.0.0.dist-info/METADATA
django_blog_comments-1.0.0.dist-info/WHEEL
django_blog_comments-1.0.0.dist-info/top_level.txt
django_blog_comments-1.0.0.dist-info/RECORD
