Metadata-Version: 2.1
Name: django-blog-comments
Version: 1.0.0
Summary: A django app which help in implementing comments in your posts model
Home-page: https://github.com/namantam1/django-blog-comments
Author: Naman Tamrakar
Author-email: namantam1@gmail.com
License: UNKNOWN
Platform: UNKNOWN
Classifier: Programming Language :: Python :: 3
Classifier: License :: OSI Approved :: MIT License
Classifier: Operating System :: OS Independent
Requires-Python: >=3.6
